prodigy_lig/__init__.py
prodigy_lig/prodigy_lig.py
prodigy_lig-1.1.4.dist-info/LICENSE
prodigy_lig-1.1.4.dist-info/WHEEL
prodigy_lig-1.1.4.dist-info/entry_points.txt
prodigy_lig-1.1.4.dist-info/METADATA
prodigy_lig-1.1.4.dist-info/RECORD
